skytag/.DS_Store
skytag/__init__.py
skytag/__version__.py
skytag/cl_utils.py
skytag/default_settings.yaml
skytag/setup.cfg
skytag/test_settings.yaml
skytag/utKit.py
skytag/commonutils/.DS_Store
skytag/commonutils/__init__.py
skytag/commonutils/getpackagepath.py
skytag/commonutils/prob_at_location.py
skytag/resources/package.mplstyle
skytag-0.3.3.dist-info/licenses/LICENSE
skytag-0.3.3.dist-info/METADATA
skytag-0.3.3.dist-info/WHEEL
skytag-0.3.3.dist-info/entry_points.txt
skytag-0.3.3.dist-info/top_level.txt
skytag-0.3.3.dist-info/RECORD
