Metadata-Version: 2.4
Name: skytag
Version: 0.3.3
Summary: Annotate transient sources or galaxies with the percentage credibility region they reside within on a given HealPix sky map.
Home-page: https://github.com/thespacedoctor/skytag
Download-URL: https://github.com/thespacedoctor/skytag/archive/v0.3.3.zip
Author: David Young
Author-email: d.r.young@qub.ac.uk
License: MIT
Keywords: astronomy
Classifier: Development Status :: 4 - Beta
Classifier: License :: OSI Approved :: MIT License
Classifier: Programming Language :: Python :: 3.7
Classifier: Topic :: Utilities
License-File: LICENSE
Requires-Dist: pyyaml
Requires-Dist: fundamentals
Requires-Dist: astropy
Requires-Dist: astropy-healpix
Requires-Dist: numpy
Requires-Dist: pandas
Dynamic: author
Dynamic: author-email
Dynamic: classifier
Dynamic: description
Dynamic: description-content-type
Dynamic: download-url
Dynamic: home-page
Dynamic: keywords
Dynamic: license
Dynamic: license-file
Dynamic: requires-dist
Dynamic: summary
